gooddata_scan_client/__init__.py
gooddata_scan_client/api_client.py
gooddata_scan_client/configuration.py
gooddata_scan_client/exceptions.py
gooddata_scan_client/model_utils.py
gooddata_scan_client/rest.py
gooddata_scan_client/api/__init__.py
gooddata_scan_client/api/actions_api.py
gooddata_scan_client/api/scanning_api.py
gooddata_scan_client/api/test_connection_api.py
gooddata_scan_client/apis/__init__.py
gooddata_scan_client/model/__init__.py
gooddata_scan_client/model/column_warning.py
gooddata_scan_client/model/data_source_parameter.py
gooddata_scan_client/model/data_source_schemata.py
gooddata_scan_client/model/declarative_column.py
gooddata_scan_client/model/declarative_table.py
gooddata_scan_client/model/declarative_tables.py
gooddata_scan_client/model/scan_request.py
gooddata_scan_client/model/scan_result_pdm.py
gooddata_scan_client/model/scan_sql_request.py
gooddata_scan_client/model/scan_sql_response.py
gooddata_scan_client/model/sql_column.py
gooddata_scan_client/model/table_warning.py
gooddata_scan_client/model/test_definition_request.py
gooddata_scan_client/model/test_query_duration.py
gooddata_scan_client/model/test_request.py
gooddata_scan_client/model/test_response.py
gooddata_scan_client/models/__init__.py
gooddata_scan_client-1.3.0.dist-info/LICENSE.txt
gooddata_scan_client-1.3.0.dist-info/METADATA
gooddata_scan_client-1.3.0.dist-info/WHEEL
gooddata_scan_client-1.3.0.dist-info/top_level.txt
gooddata_scan_client-1.3.0.dist-info/RECORD
