Metadata-Version: 2.1
Name: gooddata-scan-client
Version: 1.3.0
Summary: OpenAPI definition
Home-page: 
Author: GoodData (generated by OpenAPI Generator)
Author-email: support@gooddata.com
License: MIT
Keywords: OpenAPI,OpenAPI-Generator,OpenAPI definition
Requires-Python: >=3.6
License-File: LICENSE.txt
Requires-Dist: urllib3 (>=1.25.3)
Requires-Dist: python-dateutil
